casa_distro/__init__.py
casa_distro/admin_commands.py
casa_distro/build_workflow.py
casa_distro/bv_maker.py
casa_distro/command.py
casa_distro/defaults.py
casa_distro/docker.py
casa_distro/hash.py
casa_distro/info.py
casa_distro/log.py
casa_distro/singularity.py
casa_distro/six.py
casa_distro/user_commands.py
casa_distro-2.0.5.data/data/lib/python2.7/site-packages/casa_distro/share/distro/brainvisa/conf/bv_maker.cfg
casa_distro-2.0.5.data/data/lib/python2.7/site-packages/casa_distro/share/distro/brainvisa/conf/casa_distro.json
casa_distro-2.0.5.data/data/lib/python2.7/site-packages/casa_distro/share/distro/cati_platform/cati/qualicati/database/README
casa_distro-2.0.5.data/data/lib/python2.7/site-packages/casa_distro/share/distro/cati_platform/cati/qualicati/database_debug/README
casa_distro-2.0.5.data/data/lib/python2.7/site-packages/casa_distro/share/distro/cati_platform/cati/qualicati/save/README
casa_distro-2.0.5.data/data/lib/python2.7/site-packages/casa_distro/share/distro/cati_platform/conf/bv_maker.cfg
casa_distro-2.0.5.data/data/lib/python2.7/site-packages/casa_distro/share/distro/cati_platform/conf/casa_distro.json
casa_distro-2.0.5.data/data/lib/python2.7/site-packages/casa_distro/share/distro/cati_platform/conf/qualicati.ini
casa_distro-2.0.5.data/data/lib/python2.7/site-packages/casa_distro/share/distro/cati_platform/home/.qualicati/config.ini
casa_distro-2.0.5.data/data/lib/python2.7/site-packages/casa_distro/share/distro/cati_platform/home/.qualicati/qualicatirc
casa_distro-2.0.5.data/data/lib/python2.7/site-packages/casa_distro/share/distro/opensource/conf/bv_maker.cfg
casa_distro-2.0.5.data/data/lib/python2.7/site-packages/casa_distro/share/distro/opensource/conf/casa_distro.json
casa_distro-2.0.5.data/data/lib/python2.7/site-packages/casa_distro/share/distro/opensource/conf/svn.secret
casa_distro-2.0.5.data/scripts/casa_distro
casa_distro-2.0.5.dist-info/DESCRIPTION.rst
casa_distro-2.0.5.dist-info/METADATA
casa_distro-2.0.5.dist-info/RECORD
casa_distro-2.0.5.dist-info/WHEEL
casa_distro-2.0.5.dist-info/metadata.json
casa_distro-2.0.5.dist-info/top_level.txt
