Metadata-Version: 2.0
Name: casa-distro
Version: 2.0.5
Summary: Framework to compile BrainVISA distributions via a Singularity container.
Home-page: UNKNOWN
Author: BrainVISA team
Author-email: contact@brainvisa.info
License: CeCILL-B
Platform: UNKNOWN
Requires-Dist: six
